typetwo/__init__.py
typetwo/dictcomparer.py
typetwo/isojson.py
typetwo/rowkey.py
typetwo/transformer.py
typetwo/typetwo.py
typetwo-1.0.28.dist-info/LICENSE
typetwo-1.0.28.dist-info/METADATA
typetwo-1.0.28.dist-info/WHEEL
typetwo-1.0.28.dist-info/top_level.txt
typetwo-1.0.28.dist-info/RECORD
