Metadata-Version: 2.1
Name: typetwo
Version: 1.0.28
Summary: Helper for type-II Slowly Changing Dimensions, as well as ISO Json loading and dumping
Home-page: https://github.com/maranite/typetwo
Author: Mark White
Author-email: maranite@gmail.com
License: UNKNOWN
Project-URL: Bug Tracker, https://github.com/maranite/typetwo/issues
Project-URL: About Mark, https://www.linkedin.com/in/maranite/
Platform: UNKNOWN
Classifier: Programming Language :: Python :: 3
Classifier: License :: OSI Approved :: MIT License
Classifier: Operating System :: OS Independent
Requires-Python: >=3.8
License-File: LICENSE
Requires-Dist: pytz
